MANIFEST.in
README.md
setup.py
iglu_client/__init__.py
iglu_client/core.py
iglu_client/registries.py
iglu_client/resolver.py
iglu_client/self_describing_json.py
iglu_client.egg-info/PKG-INFO
iglu_client.egg-info/SOURCES.txt
iglu_client.egg-info/dependency_links.txt
iglu_client.egg-info/top_level.txt
iglu_client/schemas/com.snowplowanalytics.iglu/resolver-config/jsonschema/1-0-0
iglu_client/schemas/com.snowplowanalytics.iglu/resolver-config/jsonschema/1-0-1
iglu_client/schemas/com.snowplowanalytics.iglu/resolver-config/jsonschema/1-0-2
iglu_client/schemas/com.snowplowanalytics.self-desc/instance-iglu-only/jsonschema/1-0-0
tests/__init__.py
tests/test_core.py
tests/test_resolver.py
tests/test_self_describing_json.py