Metadata-Version: 2.1
Name: iglu-client
Version: 0.2.0
Summary: A python client for retrieving Iglu schemas and validating self-describing JSON
Home-page: https://github.com/jbwyme/iglu-python-client
Author: Josh Wymer
Author-email: josh@mixpanel.com
License: UNKNOWN
Platform: UNKNOWN
Classifier: Programming Language :: Python :: 3
Classifier: License :: OSI Approved :: Apache Software License
Classifier: Operating System :: OS Independent
Requires-Python: >=3.6
